myippanel/__init__.py
myippanel/errors.py
myippanel/httpclient.py
myippanel/ipclient.py
myippanel/models.py
myippanel-0.0.3.dist-info/METADATA
myippanel-0.0.3.dist-info/WHEEL
myippanel-0.0.3.dist-info/top_level.txt
myippanel-0.0.3.dist-info/RECORD
