Metadata-Version: 2.1
Name: myippanel
Version: 0.0.3
Summary: IPPANEL
Author-email: Amirreza Taherkhani <ar.taher404@gmail.com>
Classifier: Programming Language :: Python :: 3
Classifier: Operating System :: OS Independent
Requires-Python: >=3.7
